README.md
setup.py
cuemby_equinix/__init__.py
cuemby_equinix/_inputs.py
cuemby_equinix/_utilities.py
cuemby_equinix/ecxl2_connection.py
cuemby_equinix/ecxl2_connection_accepter.py
cuemby_equinix/ecxl2_serviceprofile.py
cuemby_equinix/get_ecx_port.py
cuemby_equinix/get_ecxl2_sellerprofile.py
cuemby_equinix/get_ecxl2_sellerprofiles.py
cuemby_equinix/get_metal_connection.py
cuemby_equinix/get_metal_device.py
cuemby_equinix/get_metal_device_bgp_neighbors.py
cuemby_equinix/get_metal_facility.py
cuemby_equinix/get_metal_gateway.py
cuemby_equinix/get_metal_hardware_reservation.py
cuemby_equinix/get_metal_ip_block_ranges.py
cuemby_equinix/get_metal_metro.py
cuemby_equinix/get_metal_operating_system.py
cuemby_equinix/get_metal_organization.py
cuemby_equinix/get_metal_plans.py
cuemby_equinix/get_metal_port.py
cuemby_equinix/get_metal_precreated_ip_block.py
cuemby_equinix/get_metal_project.py
cuemby_equinix/get_metal_project_ssh_key.py
cuemby_equinix/get_metal_reserved_ip_block.py
cuemby_equinix/get_metal_spot_market_price.py
cuemby_equinix/get_metal_spot_market_request.py
cuemby_equinix/get_metal_virtual_circuit.py
cuemby_equinix/get_metal_vlan.py
cuemby_equinix/get_metal_vrf.py
cuemby_equinix/get_network_account.py
cuemby_equinix/get_network_device.py
cuemby_equinix/get_network_device_platform.py
cuemby_equinix/get_network_device_software.py
cuemby_equinix/get_network_device_type.py
cuemby_equinix/metal_bgp_session.py
cuemby_equinix/metal_connection.py
cuemby_equinix/metal_device.py
cuemby_equinix/metal_device_network_type.py
cuemby_equinix/metal_gateway.py
cuemby_equinix/metal_ip_attachment.py
cuemby_equinix/metal_organization.py
cuemby_equinix/metal_port.py
cuemby_equinix/metal_port_vlan_attachment.py
cuemby_equinix/metal_project.py
cuemby_equinix/metal_project_api_key.py
cuemby_equinix/metal_project_ssh_key.py
cuemby_equinix/metal_reserved_ip_block.py
cuemby_equinix/metal_spot_market_request.py
cuemby_equinix/metal_ssh_key.py
cuemby_equinix/metal_user_api_key.py
cuemby_equinix.egg-info/PKG-INFO
cuemby_equinix.egg-info/SOURCES.txt
cuemby_equinix.egg-info/dependency_links.txt
cuemby_equinix.egg-info/not-zip-safe
cuemby_equinix.egg-info/requires.txt
cuemby_equinix.egg-info/top_level.txt
