Metadata-Version: 2.1
Name: cuemby-equinix
Version: 0.0.1a1658432893
Summary: A Pulumi package for creating and managing equinix cloud resources.
Home-page: https://www.cuemby.com
License: Apache-2.0
Project-URL: Repository, https://github.com/cuemby/pulumi-equinix
Keywords: pulumi equinix category/cloud
Platform: UNKNOWN
